{
    "document_type":  "StrategyAI_personality_v1_5_0_update_record",
    "created_at":  "2026-05-01T09:05:11",
    "repo":  "morinolink-org/morinolink-governance",
    "target_file":  "strategy_agent/keieisenryaku_personality.json",
    "before_version":  "2026-01-27-strategy-v1.4.0",
    "after_version":  "2026-05-01-strategy-v1.5.0-post150-commandroom-guarded",
    "update_classification":  "Post-150 normal operation commandroom persona update",
    "financial_scope":  {
                            "steps_140_to_147_rerun":  false,
                            "IntegratedReport_changed":  false,
                            "FullsetCache_changed":  false,
                            "OCR_changed":  false,
                            "PDF_changed":  false,
                            "financial_numbers_generated":  false
                        },
    "added_controls":  [
                           "Post-150 commandroom role",
                           "Formal tone guard",
                           "Context lock rule",
                           "High-risk labor/legal protocol",
                           "Specialist display guard",
                           "M365 data plane / GitHub-runtime control plane policy",
                           "Frozen finance scope",
                           "Validation tests"
                       ],
    "final_decision_owner":  "島田善信オーナー"
}
